ome2024_ngff_challenge/__init__.py
ome2024_ngff_challenge/lookup.py
ome2024_ngff_challenge/py.typed
ome2024_ngff_challenge/resave.py
ome2024_ngff_challenge/utils.py
ome2024_ngff_challenge/zarr_crate/__init__.py
ome2024_ngff_challenge/zarr_crate/rembi_extension.py
ome2024_ngff_challenge/zarr_crate/zarr_extension.py
ome2024_ngff_challenge-1.0.3.dist-info/LICENSE
ome2024_ngff_challenge-1.0.3.dist-info/METADATA
ome2024_ngff_challenge-1.0.3.dist-info/WHEEL
ome2024_ngff_challenge-1.0.3.dist-info/entry_points.txt
ome2024_ngff_challenge-1.0.3.dist-info/RECORD
