Metadata-Version: 2.3
Name: ome2024-ngff-challenge
Version: 1.0.3
Summary: Tools for converting OME-Zarr data within the ome2024-ngff-challenge (see https://forum.image.sc/t/ome2024-ngff-challenge/97363)
License: BSD-3-Clause
Author: Josh Moore
Author-email: josh@openmicroscopy.org
Requires-Python: >=3.10,<4.0
Classifier: Development Status :: 1 - Planning
Classifier: Intended Audience :: Developers
Classifier: Intended Audience :: Science/Research
Classifier: License :: OSI Approved :: BSD License
Classifier: Operating System :: OS Independent
Classifier: Programming Language :: Python :: 3
Classifier: Programming Language :: Python :: 3.10
Classifier: Programming Language :: Python :: 3.11
Classifier: Programming Language :: Python :: 3.12
Classifier: Programming Language :: Python :: 3.13
Classifier: Topic :: Scientific/Engineering
Classifier: Typing :: Typed
Provides-Extra: dev
Provides-Extra: docs
Provides-Extra: test
Requires-Dist: furo (>=2023.08.17) ; extra == "docs"
Requires-Dist: myst_parser (>=0.13) ; extra == "docs"
Requires-Dist: pytest (>=6) ; extra == "test" or extra == "dev"
Requires-Dist: pytest-cov (>=3) ; extra == "test" or extra == "dev"
Requires-Dist: rocrate (>=0.10,<0.11)
Requires-Dist: s3fs (>=2024.6.1)
Requires-Dist: sphinx (>=7.0) ; extra == "docs"
Requires-Dist: sphinx-autodoc-typehints ; extra == "docs"
Requires-Dist: sphinx_copybutton (>=0.3.0) ; extra == "docs"
Requires-Dist: tensorstore (>=0.1.63)
Requires-Dist: tqdm (>=4.66,<5.0)
Requires-Dist: zarr (==3.0.0a0)
Project-URL: Homepage, https://github.com/ome/ome2024-ngff-challenge
Project-URL: Repository, https://github.com/ome/ome2024-ngff-challenge
